mlbench_core/__init__.py
mlbench_core/api.py
mlbench_core/install_cuda_extensions.py
mlbench_core/aggregation/__init__.py
mlbench_core/aggregation/pytorch/__init__.py
mlbench_core/aggregation/pytorch/aggregation.py
mlbench_core/aggregation/pytorch/centralized.py
mlbench_core/aggregation/pytorch/decentralized.py
mlbench_core/cli/__init__.py
mlbench_core/cli/aws_utils.py
mlbench_core/cli/chartbuilder.py
mlbench_core/cli/cli.py
mlbench_core/cli/gcloud_utils.py
mlbench_core/cli/kind_utils.py
mlbench_core/cli/utils.py
mlbench_core/controlflow/__init__.py
mlbench_core/controlflow/pytorch/__init__.py
mlbench_core/controlflow/pytorch/checkpoints_evaluation.py
mlbench_core/controlflow/pytorch/controlflow.py
mlbench_core/controlflow/pytorch/helpers.py
mlbench_core/controlflow/pytorch/train_validation.py
mlbench_core/controlflow/tensorflow/__init__.py
mlbench_core/controlflow/tensorflow/train_validation.py
mlbench_core/dataset/__init__.py
mlbench_core/dataset/imagerecognition/__init__.py
mlbench_core/dataset/imagerecognition/pytorch/__init__.py
mlbench_core/dataset/imagerecognition/pytorch/dataloader.py
mlbench_core/dataset/imagerecognition/tensorflow/__init__.py
mlbench_core/dataset/imagerecognition/tensorflow/cifar10.py
mlbench_core/dataset/linearmodels/__init__.py
mlbench_core/dataset/linearmodels/pytorch/__init__.py
mlbench_core/dataset/linearmodels/pytorch/dataloader.py
mlbench_core/dataset/nlp/__init__.py
mlbench_core/dataset/nlp/pytorch/__init__.py
mlbench_core/dataset/nlp/pytorch/wikitext2_dataset.py
mlbench_core/dataset/nlp/pytorch/wmt16_dataset.py
mlbench_core/dataset/nlp/pytorch/wmt17_dataset.py
mlbench_core/dataset/nlp/pytorch/wmt16/__init__.py
mlbench_core/dataset/nlp/pytorch/wmt16/utils.py
mlbench_core/dataset/nlp/pytorch/wmt16/wmt16_config.py
mlbench_core/dataset/nlp/pytorch/wmt16/wmt16_tokenizer.py
mlbench_core/dataset/nlp/pytorch/wmt17/__init__.py
mlbench_core/dataset/nlp/pytorch/wmt17/batching.py
mlbench_core/dataset/nlp/pytorch/wmt17/collate.py
mlbench_core-3.0.0.dist-info/LICENSE
mlbench_core-3.0.0.dist-info/METADATA
mlbench_core-3.0.0.dist-info/WHEEL
mlbench_core-3.0.0.dist-info/entry_points.txt
mlbench_core-3.0.0.dist-info/top_level.txt
mlbench_core-3.0.0.dist-info/RECORD
