Metadata-Version: 2.1
Name: mlbench-core
Version: 3.0.0
Summary: A public and reproducible collection of reference implementations and benchmark suite for distributed machine learning systems.
Home-page: https://github.com/mlbench/mlbench_core
Author: Ralf Grubenmann
Author-email: ralf.grubenmann@epfl.ch
License: Apache Software License 2.0
Keywords: mlbench
Platform: UNKNOWN
Classifier: Development Status :: 2 - Pre-Alpha
Classifier: Intended Audience :: Developers
Classifier: License :: OSI Approved :: Apache Software License
Classifier: Natural Language :: English
Classifier: Programming Language :: Python :: 3.4
Classifier: Programming Language :: Python :: 3.5
Classifier: Programming Language :: Python :: 3.6
Classifier: Programming Language :: Python :: 3.7
Requires-Dist: appdirs (==1.4.4)
Requires-Dist: boto3 (==1.14.50)
Requires-Dist: Click (>=6.0)
Requires-Dist: deprecation (>=2.0.6)
Requires-Dist: dill (==0.3.2)
Requires-Dist: docker (==4.2.0)
Requires-Dist: GitPython (==3.1.7)
Requires-Dist: google-api-python-client (==1.12.1)
Requires-Dist: google-auth (==1.21.1)
Requires-Dist: google-cloud (==0.34.0)
Requires-Dist: google-cloud-container (==1.0.1)
Requires-Dist: grpcio (==1.31.0)
Requires-Dist: kubernetes (==11.0.0)
Requires-Dist: lmdb (==1.0.0)
Requires-Dist: matplotlib (==3.2.1)
Requires-Dist: numpy (==1.19.2)
Requires-Dist: oauth2client (==4.1.3)
Requires-Dist: sklearn (==0.0)
Requires-Dist: supermutes (==0.2.5)
Requires-Dist: tabulate (>=0.8.5)
Requires-Dist: tensorpack (==0.10.1)
Provides-Extra: dev
Requires-Dist: sacrebleu (==1.4.14) ; extra == 'dev'
Requires-Dist: torch (==1.7.0) ; extra == 'dev'
Requires-Dist: torchvision (==0.8.1) ; extra == 'dev'
Requires-Dist: tensorflow (==1.13.2) ; extra == 'dev'
Requires-Dist: black (==20.8b1) ; extra == 'dev'
Requires-Dist: isort (==5.6.4) ; extra == 'dev'
Requires-Dist: codecov (==2.1.9) ; extra == 'dev'
Requires-Dist: coverage (==5.3) ; extra == 'dev'
Requires-Dist: freezegun (==1.0.0) ; extra == 'dev'
Requires-Dist: pre-commit ; extra == 'dev'
Requires-Dist: pytest (>=3) ; extra == 'dev'
Requires-Dist: pytest-cov (==2.10.1) ; extra == 'dev'
Requires-Dist: pytest-mock (==3.3.1) ; extra == 'dev'
Requires-Dist: wcwidth (==0.2.5) ; extra == 'dev'
Provides-Extra: lint
Requires-Dist: black (==20.8b1) ; extra == 'lint'
Requires-Dist: isort (==5.6.4) ; extra == 'lint'
Provides-Extra: tensorflow
Requires-Dist: tensorflow (==1.13.2) ; extra == 'tensorflow'
Provides-Extra: test
Requires-Dist: codecov (==2.1.9) ; extra == 'test'
Requires-Dist: coverage (==5.3) ; extra == 'test'
Requires-Dist: freezegun (==1.0.0) ; extra == 'test'
Requires-Dist: pre-commit ; extra == 'test'
Requires-Dist: pytest (>=3) ; extra == 'test'
Requires-Dist: pytest-cov (==2.10.1) ; extra == 'test'
Requires-Dist: pytest-mock (==3.3.1) ; extra == 'test'
Requires-Dist: wcwidth (==0.2.5) ; extra == 'test'
Requires-Dist: black (==20.8b1) ; extra == 'test'
Requires-Dist: isort (==5.6.4) ; extra == 'test'
Requires-Dist: sacrebleu (==1.4.14) ; extra == 'test'
Requires-Dist: torch (==1.7.0) ; extra == 'test'
Requires-Dist: torchvision (==0.8.1) ; extra == 'test'
Requires-Dist: tensorflow (==1.13.2) ; extra == 'test'
Provides-Extra: torch
Requires-Dist: sacrebleu (==1.4.14) ; extra == 'torch'
Requires-Dist: torch (==1.7.0) ; extra == 'torch'
Requires-Dist: torchvision (==0.8.1) ; extra == 'torch'
